AUTHORS.rst
CONTRIBUTING.rst
HISTORY.rst
LICENSE
MANIFEST.in
README.rst
setup.cfg
setup.py
docs/Makefile
docs/authors.rst
docs/conf.py
docs/contributing.rst
docs/history.rst
docs/index.rst
docs/installation.rst
docs/make.bat
docs/readme.rst
docs/usage.rst
microparcel/__init__.py
microparcel/microparcel.py
microparcel.egg-info/PKG-INFO
microparcel.egg-info/SOURCES.txt
microparcel.egg-info/dependency_links.txt
microparcel.egg-info/entry_points.txt
microparcel.egg-info/not-zip-safe
microparcel.egg-info/requires.txt
microparcel.egg-info/top_level.txt
tests/__init__.py
tests/test_up_message.py
tests/test_up_parser.py