Metadata-Version: 1.1
Name: microparcel
Version: 0.1.1
Summary: Serialize and deserialize data from a buffer
Home-page: https://github.com/lukh/microparcel
Author: Vivien Henry
Author-email: vivien.henry@outlook.fr
License: MIT license
Keywords: microparcel
Platform: UNKNOWN
Classifier: Development Status :: 2 - Pre-Alpha
Classifier: Intended Audience :: Developers
Classifier: License :: OSI Approved :: MIT License
Classifier: Natural Language :: English
Classifier: Programming Language :: Python :: 2
Classifier: Programming Language :: Python :: 2.7
Classifier: Programming Language :: Python :: 3
Classifier: Programming Language :: Python :: 3.4
Classifier: Programming Language :: Python :: 3.5
Classifier: Programming Language :: Python :: 3.6
Classifier: Programming Language :: Python :: 3.7
